{
  "apps" : [
    {
      "name" : "随心阅",
      "versionCode" : 21,
      "versionName" : "1.1.1",
      "pkgName" : "com.pinery.reader",
      "description" : "一款随心阅读的APP",
      "content" : "随心阅是一款可以悬浮显示的阅读类软件。它分为新闻，精选阅读，自定义浏览，网址大全，四大功能。新闻功能提供包括头条，社会，科技等等类型的新闻内容。精选阅读功能同样提供各种类型的阅读。自定义浏览功能，用户可以添加自己喜欢的阅读网址。而网址大全，则提供常用的网址信息供用户浏览。随心阅的特点是可以悬浮在其他应用上显示，用户可以一边聊天一边阅读浏览想要的信息，方便易用。",
      "url" : "https://play.google.com/store/apps/details?id=com.songlin.reader",
      "iconUrl" : "http://104.225.237.137:8080/ssm/images/reader.webp"
    },
    {
      "name" : "熊猫护眼",
      "versionCode" : 1,
      "versionName" : "1.0",
      "pkgName" : "com.pinery.eye",
      "description" : "熊猫护眼，保护眼睛，拒绝熊猫眼",
      "content" : "随心阅是一款可以悬浮显示的阅读类软件。它分为新闻，精选阅读，自定义浏览，网址大全，四大功能。新闻功能提供包括头条，社会，科技等等类型的新闻内容。精选阅读功能同样提供各种类型的阅读。自定义浏览功能，用户可以添加自己喜欢的阅读网址。而网址大全，则提供常用的网址信息供用户浏览。随心阅的特点是可以悬浮在其他应用上显示，用户可以一边聊天一边阅读浏览想要的信息，方便易用。",
      "url" : "",
      "iconUrl" : ""
    }
  ]
}